LICENSE
MANIFEST.in
README.rst
setup.py
django_easygeoip.egg-info/PKG-INFO
django_easygeoip.egg-info/SOURCES.txt
django_easygeoip.egg-info/dependency_links.txt
django_easygeoip.egg-info/top_level.txt
easygeoip/__init__.py
easygeoip/settings.py
easygeoip/tasks.py
easygeoip/tests.py
easygeoip/urls_api.py
easygeoip/views.py