Metadata-Version: 1.1
Name: django-easygeoip
Version: 0.0.2
Summary: A simple Django app to include IP address-based geo-location capabilities to your project.
Home-page: http://lambdacomplete.me
Author: Marco Chiappetta
Author-email: lambdacomplete@gmail.com
License: MIT License
Platform: UNKNOWN
Classifier: Environment :: Web Environment
Classifier: Framework :: Django
Classifier: Intended Audience :: Developers
Classifier: License :: OSI Approved :: MIT License
Classifier: Operating System :: OS Independent
Classifier: Programming Language :: Python
Classifier: Programming Language :: Python :: 2
Classifier: Programming Language :: Python :: 2.7
Classifier: Topic :: Internet :: WWW/HTTP
Classifier: Topic :: Internet :: WWW/HTTP :: Dynamic Content
